XPlotLib/BandgapAnalyzer.py
XPlotLib/DOSAnalyzer.py
XPlotLib/XPlotLibUtils.py
XPlotLib/__init__.py
XPlotLib-0.0.7.dist-info/LICENSE
XPlotLib-0.0.7.dist-info/METADATA
XPlotLib-0.0.7.dist-info/WHEEL
XPlotLib-0.0.7.dist-info/top_level.txt
XPlotLib-0.0.7.dist-info/RECORD
