Metadata-Version: 2.1
Name: XPlotLib
Version: 0.0.7
Summary: Libary to plot experimental and theoretical XRay data.
Home-page: https://github.com/CMM02/XPlotLib
Author: Carl Magnus Meier
Author-email: magnus.meier@outook.de
Classifier: Programming Language :: Python :: 3
Classifier: License :: OSI Approved :: MIT License
Classifier: Operating System :: OS Independent
Requires-Python: >=3.10
License-File: LICENSE
Requires-Dist: pandas
Requires-Dist: matplotlib
Requires-Dist: numpy
Provides-Extra: dev
Requires-Dist: pytest ; extra == 'dev'
Requires-Dist: pytest-cov ; extra == 'dev'
Requires-Dist: methylcheck ; extra == 'dev'
